repo_helper_devenv/__init__.py
repo_helper_devenv/cli.py
repo_helper_devenv/py.typed
repo_helper_devenv-0.6.1.dist-info/LICENSE
repo_helper_devenv-0.6.1.dist-info/METADATA
repo_helper_devenv-0.6.1.dist-info/WHEEL
repo_helper_devenv-0.6.1.dist-info/entry_points.txt
repo_helper_devenv-0.6.1.dist-info/RECORD
