Metadata-Version: 2.1
Name: repo-helper-devenv
Version: 0.6.1
Summary: Create virtual environments with repo-helper.
Author-email: Dominic Davis-Foster <dominic@davis-foster.co.uk>
License: MIT
Keywords: repo-helper,virtualenv
Home-page: https://github.com/repo-helper/repo_helper_devenv
Project-URL: Issue Tracker, https://github.com/repo-helper/repo_helper_devenv/issues
Project-URL: Source Code, https://github.com/repo-helper/repo_helper_devenv
Project-URL: Documentation, https://repo-helper-devenv.readthedocs.io/en/latest
Platform: Windows
Platform: macOS
Platform: Linux
Classifier: License :: OSI Approved :: MIT License
Classifier: Operating System :: OS Independent
Classifier: Programming Language :: Python
Classifier: Programming Language :: Python :: 3 :: Only
Classifier: Programming Language :: Python :: 3.6
Classifier: Programming Language :: Python :: 3.7
Classifier: Programming Language :: Python :: 3.8
Classifier: Programming Language :: Python :: 3.9
Classifier: Programming Language :: Python :: 3.10
Classifier: Programming Language :: Python :: 3.11
Classifier: Programming Language :: Python :: Implementation :: CPython
Classifier: Typing :: Typed
Requires-Python: >=3.6
Requires-Dist: click>=7.1.2
Requires-Dist: consolekit>=1.0.0
Requires-Dist: deprecation-alias>=0.1.1
Requires-Dist: domdf-python-tools>=1.5.0
Requires-Dist: pyproject-devenv>=0.1.0
Requires-Dist: repo-helper>=2020.12.7
Requires-Dist: shippinglabel>=0.13.0
Requires-Dist: virtualenv>=20.1.0
